easyrun
